{
  "collectionName": "components_content_archive_ressources",
  "info": {
    "displayName": "archiveRessources",
    "description": ""
  },
  "options": {},
  "attributes": {
    "text": {
      "type": "blocks"
    },
    "image": {
      "type": "media",
      "multiple": false,
      "required": false,
      "allowedTypes": [
        "images",
        "files",
        "videos",
        "audios"
      ]
    },
    "metas": {
      "type": "component",
      "repeatable": false,
      "component": "seo.meta"
    },
    "cta": {
      "type": "component",
      "repeatable": false,
      "component": "content.call-to-action"
    }
  }
}
